[
  {
    "variant": "original_generated",
    "baseline_avg_on_ms": 125.8,
    "baseline_avg_off_ms": 118.2,
    "baseline_overhead_pct": 6.4297800338409425,
    "baseline_avg_on_cpu_ms": 128.125,
    "baseline_avg_off_cpu_ms": 121.875,
    "baseline_avg_on_heap_delta_mb": 7.556179809570312,
    "baseline_avg_off_heap_delta_mb": 3.50977783203125,
    "abnormal_avg_on_ms": 4824.4,
    "abnormal_avg_off_ms": 119.8,
    "abnormal_overhead_pct": 3927.0450751252083,
    "abnormal_avg_on_cpu_ms": 3562.5,
    "abnormal_avg_off_cpu_ms": 125,
    "abnormal_avg_on_heap_delta_mb": -30.590989685058595,
    "abnormal_avg_off_heap_delta_mb": 1.8456130981445313,
    "abnormal_flags_total": 68430,
    "session_dir": "C:\\Users\\brama\\Documents\\RD2\\src\\resultCollection\\experiments\\larva-overhead-compare\\results\\original_generated"
  },
  {
    "variant": "logging_disabled_current",
    "baseline_avg_on_ms": 120.8,
    "baseline_avg_off_ms": 105.4,
    "baseline_overhead_pct": 14.611005692599614,
    "baseline_avg_on_cpu_ms": 118.75,
    "baseline_avg_off_cpu_ms": 109.375,
    "baseline_avg_on_heap_delta_mb": 12.020391845703125,
    "baseline_avg_off_heap_delta_mb": 7.44212646484375,
    "abnormal_avg_on_ms": 851.2,
    "abnormal_avg_off_ms": 108.6,
    "abnormal_overhead_pct": 683.7937384898711,
    "abnormal_avg_on_cpu_ms": 850,
    "abnormal_avg_off_cpu_ms": 100,
    "abnormal_avg_on_heap_delta_mb": -10.623503112792969,
    "abnormal_avg_off_heap_delta_mb": 12.192765808105468,
    "abnormal_flags_total": 68430,
    "session_dir": "C:\\Users\\brama\\Documents\\RD2\\src\\resultCollection\\experiments\\larva-overhead-compare\\results\\logging_disabled_current"
  },
  {
    "variant": "optimized_no_stacktrace",
    "baseline_avg_on_ms": 120.2,
    "baseline_avg_off_ms": 112.6,
    "baseline_overhead_pct": 6.749555950266438,
    "baseline_avg_on_cpu_ms": 125,
    "baseline_avg_off_cpu_ms": 118.75,
    "baseline_avg_on_heap_delta_mb": 10.961868286132812,
    "baseline_avg_off_heap_delta_mb": 7.560420227050781,
    "abnormal_avg_on_ms": 125.8,
    "abnormal_avg_off_ms": 115,
    "abnormal_overhead_pct": 9.391304347826084,
    "abnormal_avg_on_cpu_ms": 125,
    "abnormal_avg_off_cpu_ms": 112.5,
    "abnormal_avg_on_heap_delta_mb": 13.970933532714843,
    "abnormal_avg_off_heap_delta_mb": -26.134352111816405,
    "abnormal_flags_total": 68430,
    "session_dir": "C:\\Users\\brama\\Documents\\RD2\\src\\resultCollection\\experiments\\larva-overhead-compare\\results\\optimized_no_stacktrace"
  }
]